pandasxl/__init__.py
pandasxl/excel.py
pandasxl/read.py
pandasxl-0.1.0.dist-info/METADATA
pandasxl-0.1.0.dist-info/WHEEL
pandasxl-0.1.0.dist-info/RECORD
