Metadata-Version: 2.1
Name: pandasxl
Version: 0.1.0
Summary: 
Home-page: https://github.com/jonbiemond/pandasxl
Author: Jonathan Biemond
Author-email: jonathan.biemond@devrygreenhouses.com
Requires-Python: >=3.10,<4.0
Classifier: Programming Language :: Python :: 3
Classifier: Programming Language :: Python :: 3.10
Classifier: Programming Language :: Python :: 3.11
Classifier: Programming Language :: Python :: 3.12
Requires-Dist: openpyxl (>=3.1.2,<4.0.0)
Requires-Dist: pandas (>=2.1.3,<3.0.0)
